cbr_api_gateway/__init__.py
cbr_api_gateway/fastapi/__init__.py
cbr_api_gateway/fastapi/cbr_api_gateway.py
cbr_api_gateway/utils/Version.py
cbr_api_gateway/utils/__init__.py
cbr_api_gateway/version
cbr_api_gateway-0.8.1.dist-info/LICENSE
cbr_api_gateway-0.8.1.dist-info/METADATA
cbr_api_gateway-0.8.1.dist-info/WHEEL
cbr_api_gateway-0.8.1.dist-info/RECORD
